gemini_actions_lab_cli/__init__.py
gemini_actions_lab_cli/cli.py
gemini_actions_lab_cli/env_loader.py
gemini_actions_lab_cli/github_api.py
gemini_actions_lab_cli/secrets.py
gemini_actions_lab_cli/workflow_presets.py
gemini_actions_lab_cli/workflows.py
gemini_actions_lab_cli-0.11.0.dist-info/licenses/LICENSE
gemini_actions_lab_cli-0.11.0.dist-info/METADATA
gemini_actions_lab_cli-0.11.0.dist-info/WHEEL
gemini_actions_lab_cli-0.11.0.dist-info/entry_points.txt
gemini_actions_lab_cli-0.11.0.dist-info/top_level.txt
gemini_actions_lab_cli-0.11.0.dist-info/RECORD
