Metadata-Version: 2.4
Name: gemini-actions-lab-cli
Version: 0.11.0
Summary: Command line helpers for Gemini Actions Lab repositories
Author: Sunwood AI Labs
License: MIT License
Requires-Python: >=3.11
License-File: LICENSE
Requires-Dist: requests>=2.32.3
Requires-Dist: PyNaCl>=1.5.0
Requires-Dist: pyfiglet>=0.8.post1
Requires-Dist: PyYAML>=6.0
Provides-Extra: test
Requires-Dist: pytest>=7.0.0; extra == "test"
Requires-Dist: pytest-cov>=4.0.0; extra == "test"
Dynamic: license-file
